Workbook

Sheet All Applications
A1: Company | B1: Role | C1: Status | D1: Source | E1: Date Found | F1: Date Applied | G1: Email Confirmation | H1: Local Folder
A2: Alvin College | B2: Faculty, Computer Technology (12 Month) | C2: blocked_removed | D2: Local system (job-search automation) | E2: 2026-09-03
A3: Christopher Newport University | B3: Information Security Analyst | C3: interview | D3: Local system (job-search automation) | E3: 2026-09-03 | H3: 2026-09-03_Christopher-Newport-University_Information-Security-Analyst\status.json
A4: Horry-Georgetown Technical College | B4: Information Security Officer | C4: applied | D4: Local system (job-search automation) | E4: 2026-09-03 | F4: 2026-09-05 | H4: 2026-09-03_Horry-Georgetown-Technical-College_Information-Security-Officer\status.json
A5: Rutgers, The State University of New Jersey | B5: Senior Incident Response Analyst | C5: not_pursuing | D5: Local system (job-search automation) | E5: 2026-09-03 | H5: 2026-09-03_Rutgers-University_Senior-Incident-Response-Analyst\status.json
A6: Dolby | B6: IT Audit Manager | C6: applied | D6: Email only (self-submitted, not tracked locally) | E6: 2026-09-03 | F6: 2026-09-03 | G6: Received
A7: Sallie Mae | B7: Senior Associate, Technology Audit | C7: applied | D7: Local system + email confirmed | E7: 2026-08-31 | F7: 2026-09-02 | G7: Received | H7: 2026-08-31_Sallie-Mae_Senior-Associate-Technology-Audit\status.json
A8: BNSF Railway | B8: Cybersecurity Engineer I/II (Vulnerability & Patch Management) (Remote - US) | C8: applied_unverified | D8: Local system + email confirmed | E8: 2026-09-01 | F8: 2026-09-02 | G8: Received | H8: 2026-09-01_BNSF-Railway_Cybersecurity-Engineer-Vulnerability-Patch-Management\status.json
A9: CIG Companies Services | B9: Manager, Cybersecurity | C9: applied | D9: Email only (self-submitted, not tracked locally) | E9: 2026-09-02 | F9: 2026-09-02 | G9: Received
A10: Allina Health | B10: Manager Information Security | C10: needs_manual_completion | D10: Local system (job-search automation) | E10: 2026-09-01 | H10: 2026-09-01_Allina-Health_Manager-Information-Security\status.json
A11: Carey International Group, LLC | B11: Manager, Cybersecurity | C11: not_pursuing | D11: Local system (job-search automation) | E11: 2026-09-01 | H11: 2026-09-01_Carey-International-Group_Manager-Cybersecurity\status.json
A12: City Colleges of Chicago — Olive-Harvey College | B12: Full-Time Tenure Track Faculty — Computer Information Systems (Cybersecurity) | C12: staged | D12: Local system + email confirmed | E12: 2026-09-01 | G12: Received | H12: 2026-09-01_City-Colleges-of-Chicago_Full-Time-Faculty-CIS-Cybersecurity\status.json
A13: Hewlett Packard Enterprise (HPE) | B13: Cybersecurity Operations & Enablement | C13: closed | D13: Local system (job-search automation) | E13: 2026-09-01 | H13: 2026-09-01_HPE_Cybersecurity-Operations-Enablement\status.json
A14: Hewlett Packard Enterprise (HPE) | B14: Senior Cybersecurity Transformation Lead (Enterprise Programs) | C14: not_pursuing | D14: Local system (job-search automation) | E14: 2026-09-01 | H14: 2026-09-01_HPE_Senior-Cybersecurity-Transformation-Lead-Enterprise-Programs\status.json
A15: Hewlett Packard Enterprise (HPE) | B15: Senior Manager, Enterprise OS & Virtualization | C15: not_pursuing | D15: Local system (job-search automation) | E15: 2026-09-01 | H15: 2026-09-01_HPE_Senior-Manager-Enterprise-OS-Virtualization\status.json
A16: KLA | B16: Digital Forensics & eDiscovery Manager | C16: applied | D16: Local system (job-search automation) | E16: 2026-09-01 | H16: 2026-09-01_KLA_Digital-Forensics-eDiscovery-Manager\status.json
A17: KLA | B17: IT Cybersecurity Operations Manager | C17: applied | D17: Local system (job-search automation) | E17: 2026-09-01 | H17: 2026-09-01_KLA_IT-Cybersecurity-Operations-Manager\status.json
A18: Lumiture | B18: Cyber Security Analyst | C18: applied | D18: Local system (job-search automation) | E18: 2026-09-01 | F18: 2026-09-03 | H18: 2026-09-01_Lumiture_Cyber-Security-Analyst\status.json
A19: Nebius | B19: Technical Account Manager - Token Factory | C19: rejected | D19: Local system (job-search automation) | E19: 2026-09-01 | F19: 2026-09-04 | H19: 2026-09-01_Nebius_Technical-Account-Manager-Token-Factory\status.json
A20: New Resources Consulting (client direct-hire) | B20: IT Cybersecurity Engineer | C20: applied | D20: Local system (job-search automation) | E20: 2026-09-01 | F20: 2026-09-05 | H20: 2026-09-01_New-Resources-Consulting_IT-Cybersecurity-Engineer\status.json
A21: SGMC Health | B21: Network Security Analyst, Information Services | C21: closed | D21: Local system (job-search automation) | E21: 2026-09-01 | H21: 2026-09-01_SGMC-Health_Network-Security-Analyst\status.json
A22: Travelers | B22: Cybersecurity Ops Technologist - Splunk SIEM Engineer (R-51597) | C22: staged | D22: Local system (job-search automation) | E22: 2026-09-01 | H22: 2026-09-01_Travelers_Cybersecurity-Ops-Technologist-Splunk-SIEM-Engineer\status.json
A23: Optum / UnitedHealth Group | B23: AI Security Governance Operations Specialist (listed as 'Information Security Governance Operations Support Analyst') | C23: closed | D23: Local system (job-search automation) | E23: 2026-09-01 | H23: 2026-09-01_UnitedHealth-Optum_AI-Security-Governance-Operations-Specialist\status.json
A24: University of Louisville | B24: IT Systems Engineer V (Cybersecurity Engineer) — R109233 | C24: Applied (auto-submission via Simplify) | D24: Local system (job-search automation) | E24: 2026-09-01 | F24: 2026-09-04 | G24: Discovered via Workday page banner: already applied 9/4/2026 via Simplify | H24: applications/2026-09-06_University-of-Louisville_IT-Systems-Engineer-V-Cybersecurity-Engineer-discovered
A25: University of New Hampshire | B25: Cybersecurity Operations Engineer | C25: applied | D25: Local system (job-search automation) | E25: 2026-09-01 | F25: 2026-09-04 | H25: 2026-09-01_University-of-New-Hampshire_Cybersecurity-Operations-Engineer\status.json
A26: University of Wisconsin - Madison | B26: Cybersecurity Analyst — College of Agricultural and Life Sciences (CALS) | C26: applied | D26: Local system + email confirmed | E26: 2026-09-01 | F26: 2026-09-05 | G26: Received | H26: 2026-09-01_University-of-Wisconsin-Madison_Cybersecurity-Analyst\status.json
A27: University of Wisconsin - Madison | B27: Information Systems and Web Application Security Analyst — School of Pharmacy | C27: applied | D27: Local system (job-search automation) | E27: 2026-09-01 | F27: 2026-09-03 | H27: 2026-09-01_University-of-Wisconsin-Madison_Information-Systems-and-Web-Application-Security-Analyst\status.json
A28: Verisign | B28: Manager - Information Security Compliance | C28: applied | D28: Local system (job-search automation) | E28: 2026-09-01 | F28: 2026-09-05 | H28: 2026-09-01_Verisign_Manager-Information-Security-Compliance\status.json
A29: Veritis Group Inc | B29: Technology & Cybersecurity Risk Management Analyst | C29: closed | D29: Local system (job-search automation) | E29: 2026-09-01 | H29: 2026-09-01_Veritis-Group_Technology-Cybersecurity-Risk-Management-Analyst\status.json
A30: Georgia Gwinnett College | B30: Security Operations Center (SOC) Lead | C30: needs_manual_completion | D30: Local system (job-search automation) | E30: 2026-08-31 | H30: 2026-08-31_Georgia-Gwinnett-College_Security-Operations-Center-SOC-Lead\status.json
A31: Southern New Hampshire University | B31: IAM Engineer | C31: not_pursuing | D31: Local system (job-search automation) | E31: 2026-08-31 | H31: 2026-08-31_Southern-New-Hampshire-University_IAM-Engineer\status.json
A32: Princeton University | B32: IT Risk & Information Security Analyst (University Services) | C32: applied | D32: Local system (job-search automation) | E32: 2026-08-22 | F32: 2026-08-30 | H32: 2026-08-22_Princeton-University_IT-Risk-and-Information-Security-Analyst\status.json
A33: Albany Medical Center | B33: IT Security Manager | C33: applied | D33: Local system + email confirmed | E33: 2026-08-29 | F33: 2026-08-30 | G33: Rejected | H33: 2026-08-29_Albany-Medical-Center_IT-Security-Manager\status.json
A34: IBM | B34: Advisory Data Scientist, IBM Quantum | C34: rejected | D34: Local system + email confirmed | E34: 2026-08-29 | F34: 2026-08-30 | G34: Received | H34: 2026-08-29_IBM_Advisory-Data-Scientist-IBM-Quantum\status.json
A35: The MITRE Corporation | B35: Internships in Cybersecurity and Information Security (general talent pool, not a specific role) | C35: applied | D35: Local system (job-search automation) | E35: 2026-08-29 | F35: 2026-08-30 | H35: 2026-08-29_MITRE-Corporation_Cybersecurity-Internship\status.json
A36: Nebius | B36: DC Operations Manager - Critical Infrastructure | C36: applied | D36: Local system + email confirmed | E36: 2026-08-30 | F36: 2026-08-30 | G36: Received | H36: 2026-08-30_Nebius_DC-Operations-Manager-Critical-Infrastructure\status.json
A37: Nebius | B37: IT Risks & Control Manager | C37: applied | D37: Local system (job-search automation) | E37: 2026-08-30 | F37: 2026-08-30 | H37: 2026-08-30_Nebius_IT-Risks-Control-Manager\status.json
A38: Team Cymru | B38: Technical Trainer - Curriculum Developer | C38: applied | D38: Local system (job-search automation) | E38: 2026-08-30 | F38: 2026-08-30 | H38: 2026-08-30_Team-Cymru_Technical-Trainer-Curriculum-Developer\status.json
A39: Wake Technical Community College | B39: Instructor 9M Cybersecurity, Digital Forensics | C39: not_pursuing | D39: Local system (job-search automation) | E39: 2026-08-30 | H39: 2026-08-30_Wake-Technical-Community-College_Instructor-Cybersecurity-Digital-Forensics\status.json
A40: Aquent | Skill | B40: Fraud Analytics & Strategy Manager | C40: applied | D40: Email only (self-submitted, not tracked locally) | E40: 2026-08-30 | F40: 2026-08-30 | G40: Received
A41: Aquent | Skill | B41: IT - Cyber Security Developer | C41: applied | D41: Email only (self-submitted, not tracked locally) | E41: 2026-08-30 | F41: 2026-08-30 | G41: Received
A42: Spectrum Comm Inc | B42: Systems Analyst | C42: rejected | D42: Email only (self-submitted, not tracked locally) | E42: 2026-08-30 | F42: 2026-08-30 | G42: Rejected
A43: MetroStar | B43: (role not specified in confirmation) | C43: applied | D43: Email only (self-submitted, not tracked locally) | E43: 2026-08-30 | F43: 2026-08-30 | G43: Received
A44: Iron Bow Technologies | B44: PKI, Cryptography and Zero Trust Architect | C44: applied | D44: Email only (self-submitted, not tracked locally) | E44: 2026-08-30 | F44: 2026-08-30 | G44: Received
A45: Iron Bow Technologies | B45: Post-Quantum Cryptography Specialist | C45: applied | D45: Email only (self-submitted, not tracked locally) | E45: 2026-08-30 | F45: 2026-08-30 | G45: Received
A46: Authentic Brands Group | B46: Manager, IT Security and Compliance | C46: applied | D46: Email only (self-submitted, not tracked locally) | E46: 2026-08-30 | F46: 2026-08-30 | G46: Received
A47: Riverside Community College District (Moreno Valley College) | B47: Computer Information Systems Instructor - Cybersecurity Emphasis | C47: applied | D47: Local system (job-search automation) | E47: 2026-08-26 | F47: 2026-08-29 | H47: 2026-08-26_Riverside-Community-College-District_CIS-Instructor-Cybersecurity-Emphasis\status.json
A48: University of Vermont | B48: Artificial Intelligence and Modern Work Specialist | C48: applied | D48: Local system + email confirmed | E48: 2026-08-27 | F48: 2026-08-29 | G48: Received | H48: 2026-08-27_University-of-Vermont_AI-and-Modern-Work-Specialist\status.json
A49: Valsoft Corporation | B49: Compliance, Security & AI Governance Analyst | C49: applied | D49: Local system + email confirmed | E49: 2026-08-29 | F49: 2026-08-29 | G49: Received | H49: 2026-08-27_Valsoft-Corporation_Compliance-Security-and-AI-Governance-Analyst\status.json
A50: Polsinelli PC | B50: Governance Risk and Compliance Analyst | C50: applied | D50: Local system + email confirmed | E50: 2026-08-28 | F50: 2026-08-29 | G50: Received | H50: 2026-08-28_Polsinelli-PC_Governance-Risk-and-Compliance-Analyst\status.json
A51: A-Alpha Bio | B51: Manager, Information Security & Technology | C51: applied | D51: Local system + email confirmed | E51: 2026-08-29 | F51: 2026-08-29 | G51: Received | H51: 2026-08-29_A-Alpha-Bio_Manager-Information-Security-Technology\status.json
A52: Allied Benefit Systems | B52: GRC Analyst | C52: applied | D52: Local system + email confirmed | E52: 2026-08-29 | F52: 2026-08-29 | G52: Received | H52: 2026-08-29_Allied-Benefit-Systems_GRC-Analyst\status.json
A53: Commence | B53: IT Security Governance Officer | C53: applied | D53: Local system + email confirmed | E53: 2026-08-29 | F53: 2026-08-29 | G53: Received | H53: 2026-08-29_Commence_IT-Security-Governance-Officer\status.json
A54: Elevance Health | B54: Cybersecurity PCI Compliance Advisor | C54: applied | D54: Local system + email confirmed | E54: 2026-08-29 | F54: 2026-08-29 | G54: Received | H54: 2026-08-29_Elevance-Health_Cybersecurity-PCI-Compliance-Advisor\status.json
A55: Grinnell College | B55: Department of Computer Science (Tenure Track, Start Fall 2027) | C55: not_pursuing | D55: Local system (job-search automation) | E55: 2026-08-29 | H55: 2026-08-29_Grinnell-College_Computer-Science-Tenure-Track\status.json
A56: Hillsborough Community College | B56: Computer Science Instructor | C56: not_pursuing | D56: Local system (job-search automation) | E56: 2026-08-29 | H56: 2026-08-29_Hillsborough-Community-College_Computer-Science-Instructor\status.json
A57: IBM | B57: Intern Security Consultant - Cyber Strategy & Risk 2027 | C57: rejected | D57: Local system (job-search automation) | E57: 2026-08-29 | F57: 2026-08-29 | H57: 2026-08-29_IBM_Intern-Security-Consultant-Cyber-Strategy-Risk-2027\status.json
A58: Legora | B58: GRC Lead | C58: rejected | D58: Local system + email confirmed | E58: 2026-08-29 | F58: 2026-08-29 | G58: Rejected | H58: 2026-08-29_Legora_GRC-Lead\status.json
A59: Lincoln Financial | B59: Sr Associate Cybersecurity Risk Analyst | C59: applied | D59: Local system (job-search automation) | E59: 2026-08-29 | F59: 2026-08-29 | H59: 2026-08-29_Lincoln-Financial_Sr-Associate-Cybersecurity-Risk-Analyst\status.json
A60: The MITRE Corporation | B60: Cyber Defense Intern | C60: not_pursuing | D60: Local system (job-search automation) | E60: 2026-08-29 | H60: 2026-08-29_MITRE-Corporation_Cyber-Defense-Intern\status.json
A61: Origami Risk LLC | B61: AI Governance Analyst | C61: applied | D61: Local system + email confirmed | E61: 2026-08-29 | F61: 2026-08-29 | G61: Received | H61: 2026-08-29_Origami-Risk_AI-Governance-Analyst\status.json
A62: Protective | B62: Security GRC Analyst | C62: applied | D62: Local system (job-search automation) | E62: 2026-08-29 | F62: 2026-08-29 | H62: 2026-08-29_Protective_Security-GRC-Analyst\status.json
A63: Sun Communities, Inc. | B63: Manager, IT Security | C63: applied | D63: Local system + email confirmed | E63: 2026-08-29 | F63: 2026-08-29 | G63: Received | H63: 2026-08-29_Sun-Communities_Manager-IT-Security\status.json
A64: Truist Financial Corporation | B64: Cyber Incident Management Engineer | C64: not_pursuing | D64: Local system (job-search automation) | E64: 2026-08-29 | H64: 2026-08-29_Truist_Cyber-Incident-Management-Engineer\status.json
A65: UnitedHealth Group / Optum | B65: AI Security Governance Operations Specialist (Information Security Governance Operations Support Analyst) | C65: applied | D65: Local system + email confirmed | E65: 2026-08-29 | F65: 2026-08-29 | G65: Received - Next Stage | H65: 2026-08-29_UnitedHealth-Group-Optum_AI-Security-Governance-Operations-Specialist\status.json
A66: The University of Texas at Arlington | B66: Cybersecurity Compliance Analyst | C66: applied | D66: Local system + email confirmed | E66: 2026-08-24 | F66: 2026-08-28 | G66: Received | H66: 2026-08-24_University-of-Texas-at-Arlington_Cybersecurity-Compliance-Analyst\status.json
A67: University of Oklahoma Libraries | B67: Research Data and AI Specialist | C67: applied | D67: Local system (job-search automation) | E67: 2026-08-26 | F67: 2026-08-28 | H67: 2026-08-26_University-of-Oklahoma_Research-Data-and-AI-Specialist\status.json
A68: Cummins Inc. | B68: Cybersecurity Assurance Analyst | C68: applied | D68: Local system + email confirmed | E68: 2026-08-27 | F68: 2026-08-28 | G68: Received | H68: 2026-08-27_Cummins-Inc_Cybersecurity-Assurance-Analyst\status.json
A69: University of North Carolina School of the Arts | B69: IT Security Professional I / Cybersecurity Analyst | C69: applied | D69: Local system (job-search automation) | E69: 2026-08-27 | F69: 2026-08-28 | H69: 2026-08-27_UNC-School-of-the-Arts_IT-Security-Professional-I-Cybersecurity-Analyst\status.json
A70: University of Texas at Arlington | B70: Identity & Access Analyst II | C70: applied | D70: Local system (job-search automation) | E70: 2026-08-27 | F70: 2026-08-28 | H70: 2026-08-27_University-of-Texas-at-Arlington_Identity-and-Access-Analyst-II\status.json
A71: mTrade, LLC | B71: Senior Cybersecurity Risk & Governance Analyst | C71: applied | D71: Local system (job-search automation) | E71: 2026-08-27 | F71: 2026-08-28 | H71: 2026-08-27_mTrade-LLC_Senior-Cybersecurity-Risk-and-Governance-Analyst\status.json
A72: Carnegie Mellon University | B72: Sr. Research IT Security Risk and Compliance Analyst - Computing Services | C72: applied | D72: Local system (job-search automation) | E72: 2026-08-22 | F72: 2026-08-27 | H72: 2026-08-22_Carnegie-Mellon-University_Sr-Research-IT-Security-Risk-and-Compliance-Analyst\status.json
A73: Cogent Communications | B73: Cybersecurity Analyst, Security and AI Governance | C73: applied | D73: Local system (job-search automation) | E73: 2026-08-23 | F73: 2026-08-27 | H73: 2026-08-23_Cogent-Communications_Cybersecurity-Analyst-Security-and-AI-Governance\status.json
A74: Roxbury Community College | B74: IT Operations and Network Infrastructure Engineer | C74: applied | D74: Local system (job-search automation) | E74: 2026-08-23 | F74: 2026-08-27 | H74: 2026-08-23_Roxbury-Community-College_IT-Operations-and-Network-Infrastructure-Engineer\status.json
A75: University of New Mexico | B75: Core IT Svcs Splst (req37653) | C75: applied | D75: Local system + email confirmed | E75: 2026-08-23 | F75: 2026-08-27 | G75: Received | H75: 2026-08-23_University-of-New-Mexico_Core-IT-Services-Specialist\status.json
A76: Kroll | B76: Senior Associate, Incident Response | C76: applied | D76: Local system (job-search automation) | E76: 2026-08-25 | F76: 2026-08-27 | H76: 2026-08-25_Kroll_Senior-Associate-Incident-Response\status.json
A77: Lighthouse | B77: Digital Forensics Analyst | C77: applied | D77: Local system + email confirmed | E77: 2026-08-25 | F77: 2026-08-27 | G77: Received | H77: 2026-08-25_Lighthouse_Digital-Forensics-Analyst\status.json
A78: Neumo | B78: Manager, Information Security (GRC) (Remote) | C78: applied | D78: Local system + email confirmed | E78: 2026-08-25 | F78: 2026-08-27 | G78: Received | H78: 2026-08-25_Neumo_Manager-Information-Security-GRC\status.json
A79: New York University | B79: Information Security Analyst Tier 1 | C79: applied | D79: Local system (job-search automation) | E79: 2026-08-25 | F79: 2026-08-27 | H79: 2026-08-25_New-York-University_Information-Security-Analyst-Tier-1\status.json
A80: Utah Valley University | B80: Site Reliability Engineer III - Operations | C80: applied | D80: Local system + email confirmed | E80: 2026-08-25 | F80: 2026-08-27 | G80: Received | H80: 2026-08-25_Utah-Valley-University_Site-Reliability-Engineer-III-Operations\status.json
A81: Vector3, Inc. (Tokio Marine HCC) | B81: Cyber Threat Analyst | C81: applied | D81: Local system + email confirmed | E81: 2026-08-25 | F81: 2026-08-27 | G81: Received | H81: 2026-08-25_Vector3-Tokio-Marine-HCC_Cyber-Threat-Analyst\status.json
A82: Stony Brook University | B82: Programmer Analyst Info Security | C82: applied | D82: Local system (job-search automation) | E82: 2026-08-26 | F82: 2026-08-27 | H82: 2026-08-26_Stony-Brook-University_Programmer-Analyst-Info-Security\status.json
A83: CBRE | B83: Cybersecurity IT Audit Manager | C83: not_pursuing | D83: Local system (job-search automation) | E83: 2026-08-27 | H83: 2026-08-27_CBRE_Cybersecurity-IT-Audit-Manager\status.json
A84: TripleTen | B84: Cybersecurity Teaching Experts | C84: not_pursuing | D84: Local system (job-search automation) | E84: 2026-08-27 | H84: 2026-08-27_TripleTen_Cybersecurity-Teaching-Experts\status.json
A85: University of Nevada, Reno | B85: Information Security Analyst, Office of Information Technology | C85: applied | D85: Local system (job-search automation) | E85: 2026-08-27 | F85: 2026-08-27 | H85: 2026-08-27_University-of-Nevada-Reno_Information-Security-Analyst\status.json
A86: Carnegie Mellon University | B86: IT Security Engineer - Computing Services | C86: applied | D86: Local system + email confirmed | E86: 2026-08-22 | F86: 2026-08-26 | G86: Received | H86: 2026-08-22_Carnegie-Mellon-University_IT-Security-Engineer\status.json
A87: East Carolina University | B87: Technology Support Analyst - Journey | C87: applied | D87: Local system (job-search automation) | E87: 2026-08-25 | F87: 2026-08-26 | H87: 2026-08-25_East-Carolina-University_Technology-Support-Analyst-Journey\status.json
A88: BigCommerce | B88: Security Governance, Risk & Compliance Analyst I | C88: applied | D88: Local system (job-search automation) | E88: 2026-08-24 | F88: 2026-08-25 | H88: 2026-08-24_BigCommerce_Security-GRC-Analyst-I\status.json
A89: Blackstone | B89: Threat Intelligence Analyst, Associate - Security Operations | C89: applied | D89: Local system (job-search automation) | E89: 2026-08-24 | F89: 2026-08-25 | H89: 2026-08-24_Blackstone_Threat-Intelligence-Analyst-Associate\status.json
A90: Kaskaskia College | B90: Asst. Professor of Cybersecurity and Network Administration | C90: applied | D90: Local system + email confirmed | E90: 2026-08-24 | F90: 2026-08-25 | G90: Received | H90: 2026-08-24_Kaskaskia-College_Assistant-Professor-Cybersecurity-and-Network-Administration\status.json
A91: NetCov (Network Coverage) | B91: GRC Analyst | C91: applied | D91: Local system + email confirmed | E91: 2026-08-24 | F91: 2026-08-25 | G91: Received | H91: 2026-08-24_NetCov_GRC-Analyst\status.json
A92: Huntington Bank | B92: Manager of Cybersecurity Strategy and Governance | C92: applied | D92: Local system (job-search automation) | E92: 2026-08-25 | F92: 2026-08-25 | H92: 2026-08-25_Huntington-Bank_Manager-Cybersecurity-Strategy-and-Governance\status.json
A93: Huntress | B93: Senior Technical Trainer - Security | C93: applied | D93: Local system + email confirmed | E93: 2026-08-25 | F93: 2026-08-25 | G93: Received | H93: 2026-08-25_Huntress_Senior-Technical-Trainer-Security\status.json
A94: Texas A&M University-Kingsville | B94: Security Analyst I | C94: closed | D94: Local system (job-search automation) | E94: 2026-08-25 | H94: 2026-08-25_Texas-A-and-M-University-Kingsville_Security-Analyst-I\status.json
A95: CardWorks | B95: Director, Security Risk Management | C95: rejected | D95: Email only (self-submitted, not tracked locally) | E95: 2026-08-25 | F95: 2026-08-25 | G95: Rejected
A96: Healthcare Shares | B96: Cyber Risk Quantification | C96: applied | D96: Local system (job-search automation) | E96: 2026-08-24 | F96: 2026-08-24 | H96: 2026-08-24_Healthcare-Shares_Cyber-Risk-Quantification\status.json
A97: JPMorganChase | B97: Hiring Event - Security Architecture & Engineering (Sep 24-25, 2026) | C97: applied | D97: Local system (job-search automation) | E97: 2026-08-24 | F97: 2026-08-24 | H97: 2026-08-24_JPMorganChase_Security-Architecture-Engineering-Hiring-Event\status.json
A98: St. Mary's College of Maryland | B98: Systems Administrator / Senior Systems Administrator | C98: needs_manual_completion | D98: Local system (job-search automation) | E98: 2026-08-24 | H98: 2026-08-24_St-Marys-College-of-Maryland_Systems-Administrator\status.json
A99: System Soft Technologies | B99: Senior Privacy Analyst | C99: applied | D99: Local system (job-search automation) | E99: 2026-08-24 | F99: 2026-08-24 | H99: 2026-08-24_System-Soft-Technologies_Senior-Privacy-Analyst\status.json
A100: Antier Solutions Pvt. Ltd | B100: Cybersecurity Trainer | C100: applied | D100: Email only (self-submitted, not tracked locally) | E100: 2026-08-24 | F100: 2026-08-24 | G100: Received
...

Sheet Summary
B2: Job Search Tracker — Summary
B3: Combines applications tracked by the automated job-search system with confirmation emails found in Gmail (inbox + trash)
B5: Total Unique Applications Tracked | C5: =COUNTA('All Applications'!A2:A140)
B7: By Status
B8: applied | C8: =COUNTIF('All Applications'!C2:C140,"applied")
B9: interview | C9: =COUNTIF('All Applications'!C2:C140,"interview")
B10: applied_unverified | C10: =COUNTIF('All Applications'!C2:C140,"applied_unverified")
B11: staged | C11: =COUNTIF('All Applications'!C2:C140,"staged")
B12: needs_manual_completion | C12: =COUNTIF('All Applications'!C2:C140,"needs_manual_completion")
B13: rejected | C13: =COUNTIF('All Applications'!C2:C140,"rejected")
B14: not_pursuing | C14: =COUNTIF('All Applications'!C2:C140,"not_pursuing")
B15: closed | C15: =COUNTIF('All Applications'!C2:C140,"closed")
B17: By Source
B18: Local system + email confirmed | C18: =COUNTIF('All Applications'!D2:D140,"Local system + email confirmed")
B19: Local system (job-search automation) | C19: =COUNTIF('All Applications'!D2:D140,"Local system (job-search automation)")
B20: Email only (self-submitted, not tracked locally) | C20: =COUNTIF('All Applications'!D2:D140,"Email only (self-submitted, not tracked locally)")
B22: By Month (Date Applied/Found)
B23: Note: a row counts in two months if its Found and Applied dates differ.
B24: 2025-12 | C24: =SUMPRODUCT((LEFT('All Applications'!E2:E140,7)="2025-12")*1)+SUMPRODUCT((LEFT('All Applications'!E2:E140,7)<>"2025-12")*(LEFT('All Applications'!F2:F140,7)="2025-12")*1)
B25: 2026-01 | C25: =SUMPRODUCT((LEFT('All Applications'!E2:E140,7)="2026-01")*1)+SUMPRODUCT((LEFT('All Applications'!E2:E140,7)<>"2026-01")*(LEFT('All Applications'!F2:F140,7)="2026-01")*1)
B26: 2026-02 | C26: =SUMPRODUCT((LEFT('All Applications'!E2:E140,7)="2026-02")*1)+SUMPRODUCT((LEFT('All Applications'!E2:E140,7)<>"2026-02")*(LEFT('All Applications'!F2:F140,7)="2026-02")*1)
B27: 2026-03 | C27: =SUMPRODUCT((LEFT('All Applications'!E2:E140,7)="2026-03")*1)+SUMPRODUCT((LEFT('All Applications'!E2:E140,7)<>"2026-03")*(LEFT('All Applications'!F2:F140,7)="2026-03")*1)
B28: 2026-04 | C28: =SUMPRODUCT((LEFT('All Applications'!E2:E140,7)="2026-04")*1)+SUMPRODUCT((LEFT('All Applications'!E2:E140,7)<>"2026-04")*(LEFT('All Applications'!F2:F140,7)="2026-04")*1)
B29: 2026-05 | C29: =SUMPRODUCT((LEFT('All Applications'!E2:E140,7)="2026-05")*1)+SUMPRODUCT((LEFT('All Applications'!E2:E140,7)<>"2026-05")*(LEFT('All Applications'!F2:F140,7)="2026-05")*1)
B30: 2026-06 | C30: =SUMPRODUCT((LEFT('All Applications'!E2:E140,7)="2026-06")*1)+SUMPRODUCT((LEFT('All Applications'!E2:E140,7)<>"2026-06")*(LEFT('All Applications'!F2:F140,7)="2026-06")*1)
B31: 2026-07 | C31: =SUMPRODUCT((LEFT('All Applications'!E2:E140,7)="2026-07")*1)+SUMPRODUCT((LEFT('All Applications'!E2:E140,7)<>"2026-07")*(LEFT('All Applications'!F2:F140,7)="2026-07")*1)
B32: 2026-08 | C32: =SUMPRODUCT((LEFT('All Applications'!E2:E140,7)="2026-08")*1)+SUMPRODUCT((LEFT('All Applications'!E2:E140,7)<>"2026-08")*(LEFT('All Applications'!F2:F140,7)="2026-08")*1)
B33: 2026-09 | C33: =SUMPRODUCT((LEFT('All Applications'!E2:E140,7)="2026-09")*1)+SUMPRODUCT((LEFT('All Applications'!E2:E140,7)<>"2026-09")*(LEFT('All Applications'!F2:F140,7)="2026-09")*1)

Sheet Email-Only Applications
A1: Date | B1: Company | C1: Role | D1: Email Status | E1: Gmail Folder
A2: 2026-09-03 | B2: Dolby | C2: IT Audit Manager | D2: Received | E2: INBOX
A3: 2026-09-02 | B3: CIG Companies Services | C3: Manager, Cybersecurity | D3: Received | E3: TRASH
A4: 2026-08-30 | B4: Aquent | Skill | C4: Fraud Analytics & Strategy Manager | D4: Received | E4: TRASH
A5: 2026-08-30 | B5: Aquent | Skill | C5: IT - Cyber Security Developer | D5: Received | E5: TRASH
A6: 2026-08-30 | B6: Spectrum Comm Inc | C6: Systems Analyst | D6: Rejected | E6: TRASH
A7: 2026-08-30 | B7: MetroStar | C7: (role not specified in confirmation) | D7: Received | E7: TRASH
A8: 2026-08-30 | B8: Iron Bow Technologies | C8: PKI, Cryptography and Zero Trust Architect | D8: Received | E8: TRASH
A9: 2026-08-30 | B9: Iron Bow Technologies | C9: Post-Quantum Cryptography Specialist | D9: Received | E9: TRASH
A10: 2026-08-30 | B10: Authentic Brands Group | C10: Manager, IT Security and Compliance | D10: Received | E10: TRASH
A11: 2026-08-25 | B11: CardWorks | C11: Director, Security Risk Management | D11: Rejected | E11: TRASH
A12: 2026-08-24 | B12: Antier Solutions Pvt. Ltd | C12: Cybersecurity Trainer | D12: Received | E12: TRASH
... A39: 2026-08-08 | B39: Horry County, SC | C39: (role not specified in confirmation) | D39: Received | E39: TRASH
